{
  "timestamp": "2026-06-03T11:31:54.910987",
  "file_path": "/Users/kostantinkrivula/Desktop/Kronos-master/data/XSHG_5min_600977.csv",
  "prediction_type": "Kronos model prediction (within selected window: first 400 data points for prediction, last 120 data points for comparison, time span: 9 days 05:45:00)",
  "prediction_params": {
    "lookback": 400,
    "pred_len": 120,
    "temperature": 1.0,
    "top_p": 0.9,
    "sample_count": 1,
    "start_date": "2025-09-05T18:58"
  },
  "input_data_summary": {
    "rows": 400,
    "columns": [
      "open",
      "high",
      "low",
      "close",
      "volume"
    ],
    "price_range": {
      "open": {
        "min": 133.2,
        "max": 156.6
      },
      "high": {
        "min": 135.2,
        "max": 156.8
      },
      "low": {
        "min": 133.1,
        "max": 156.3
      },
      "close": {
        "min": 135.0,
        "max": 156.6
      }
    },
    "last_values": {
      "open": 155.9,
      "high": 156.8,
      "low": 155.0,
      "close": 155.2
    }
  },
  "prediction_results": [
    {
      "timestamp": "2025-09-16T09:55:00",
      "open": 155.5508575439453,
      "high": 156.3904266357422,
      "low": 155.45201110839844,
      "close": 156.0921173095703,
      "volume": 2775187.0,
      "amount": 413978368.0
    },
    {
      "timestamp": "2025-09-16T10:00:00",
      "open": 155.7664031982422,
      "high": 155.8063201904297,
      "low": 155.2429656982422,
      "close": 155.37948608398438,
      "volume": 1993201.25,
      "amount": 295270848.0
    },
    {
      "timestamp": "2025-09-16T10:05:00",
      "open": 155.43072509765625,
      "high": 155.95677185058594,
      "low": 155.1576385498047,
      "close": 155.6883087158203,
      "volume": 3245091.75,
      "amount": 483101280.0
    },
    {
      "timestamp": "2025-09-16T10:10:00",
      "open": 155.61199951171875,
      "high": 155.99749755859375,
      "low": 155.32925415039062,
      "close": 155.7615203857422,
      "volume": 1686844.0,
      "amount": 251146304.0
    },
    {
      "timestamp": "2025-09-16T10:15:00",
      "open": 155.78768920898438,
      "high": 156.28782653808594,
      "low": 155.34811401367188,
      "close": 155.935546875,
      "volume": 2408701.5,
      "amount": 358976480.0
    },
    {
      "timestamp": "2025-09-16T10:20:00",
      "open": 155.83123779296875,
      "high": 156.10855102539062,
      "low": 155.40646362304688,
      "close": 155.76675415039062,
      "volume": 2214135.0,
      "amount": 329715264.0
    },
    {
      "timestamp": "2025-09-16T10:25:00",
      "open": 155.58090209960938,
      "high": 155.93963623046875,
      "low": 155.30703735351562,
      "close": 155.69500732421875,
      "volume": 2176673.75,
      "amount": 324481472.0
    },
    {
      "timestamp": "2025-09-16T10:30:00",
      "open": 155.56690979003906,
      "high": 155.92874145507812,
      "low": 155.36187744140625,
      "close": 155.72291564941406,
      "volume": 1506904.125,
      "amount": 224094816.0
    },
    {
      "timestamp": "2025-09-16T10:35:00",
      "open": 155.60414123535156,
      "high": 155.89447021484375,
      "low": 155.28929138183594,
      "close": 155.6328582763672,
      "volume": 2020070.5,
      "amount": 302060288.0
    },
    {
      "timestamp": "2025-09-16T10:40:00",
      "open": 155.4993896484375,
      "high": 155.86061096191406,
      "low": 155.24334716796875,
      "close": 155.62294006347656,
      "volume": 2084157.0,
      "amount": 311211456.0
    },
    {
      "timestamp": "2025-09-16T10:45:00",
      "open": 155.61097717285156,
      "high": 155.8077850341797,
      "low": 155.116943359375,
      "close": 155.41311645507812,
      "volume": 2801455.5,
      "amount": 418816736.0
    },
    {
      "timestamp": "2025-09-16T10:50:00",
      "open": 155.25425720214844,
      "high": 155.42762756347656,
      "low": 154.7465057373047,
      "close": 154.99195861816406,
      "volume": 2201204.5,
      "amount": 328535552.0
    },
    {
      "timestamp": "2025-09-16T10:55:00",
      "open": 154.9503173828125,
      "high": 155.20452880859375,
      "low": 154.6850128173828,
      "close": 154.94073486328125,
      "volume": 1796167.75,
      "amount": 265637216.0
    },
    {
      "timestamp": "2025-09-16T11:00:00",
      "open": 154.89854431152344,
      "high": 155.01902770996094,
      "low": 154.3489227294922,
      "close": 154.5604705810547,
      "volume": 2648601.25,
      "amount": 393821984.0
    },
    {
      "timestamp": "2025-09-16T11:05:00",
      "open": 154.3990936279297,
      "high": 154.5479278564453,
      "low": 153.83999633789062,
      "close": 154.05453491210938,
      "volume": 2047238.75,
      "amount": 302437568.0
    },
    {
      "timestamp": "2025-09-16T11:10:00",
      "open": 154.37643432617188,
      "high": 154.96229553222656,
      "low": 153.61526489257812,
      "close": 153.81312561035156,
      "volume": 1794896.0,
      "amount": 265693008.0
    },
    {
      "timestamp": "2025-09-16T11:15:00",
      "open": 153.80984497070312,
      "high": 154.0339813232422,
      "low": 153.23757934570312,
      "close": 153.4540252685547,
      "volume": 2556803.0,
      "amount": 378050208.0
    },
    {
      "timestamp": "2025-09-16T11:20:00",
      "open": 153.4855499267578,
      "high": 154.1595916748047,
      "low": 153.3520965576172,
      "close": 154.02288818359375,
      "volume": 2243509.5,
      "amount": 330844928.0
    },
    {
      "timestamp": "2025-09-16T11:25:00",
      "open": 153.8954315185547,
      "high": 154.2251434326172,
      "low": 153.68846130371094,
      "close": 153.98583984375,
      "volume": 1309420.875,
      "amount": 189634464.0
    },
    {
      "timestamp": "2025-09-16T11:30:00",
      "open": 153.80801391601562,
      "high": 153.8963623046875,
      "low": 153.3824920654297,
      "close": 153.53277587890625,
      "volume": 1092803.5,
      "amount": 157717200.0
    },
    {
      "timestamp": "2025-09-16T11:35:00",
      "open": 153.36769104003906,
      "high": 153.4400177001953,
      "low": 152.7498016357422,
      "close": 152.89512634277344,
      "volume": 1680109.5,
      "amount": 248690992.0
    },
    {
      "timestamp": "2025-09-16T11:40:00",
      "open": 152.76625061035156,
      "high": 152.9495849609375,
      "low": 152.09767150878906,
      "close": 152.46484375,
      "volume": 3971179.5,
      "amount": 581836160.0
    },
    {
      "timestamp": "2025-09-16T11:45:00",
      "open": 152.27806091308594,
      "high": 152.8638458251953,
      "low": 151.9598388671875,
      "close": 152.45355224609375,
      "volume": 2468444.25,
      "amount": 355141440.0
    },
    {
      "timestamp": "2025-09-16T11:50:00",
      "open": 152.4796600341797,
      "high": 152.8688507080078,
      "low": 152.26242065429688,
      "close": 152.66650390625,
      "volume": 1234386.875,
      "amount": 178086144.0
    },
    {
      "timestamp": "2025-09-16T11:55:00",
      "open": 152.99853515625,
      "high": 153.44644165039062,
      "low": 152.0091552734375,
      "close": 152.13259887695312,
      "volume": 1542095.5,
      "amount": 226434320.0
    },
    {
      "timestamp": "2025-09-16T12:00:00",
      "open": 152.12281799316406,
      "high": 152.4242706298828,
      "low": 151.65814208984375,
      "close": 151.92727661132812,
      "volume": 2355158.25,
      "amount": 347270784.0
    },
    {
      "timestamp": "2025-09-16T12:05:00",
      "open": 151.83407592773438,
      "high": 152.12698364257812,
      "low": 151.4414520263672,
      "close": 151.73648071289062,
      "volume": 2473606.75,
      "amount": 363344704.0
    },
    {
      "timestamp": "2025-09-16T12:10:00",
      "open": 151.9663543701172,
      "high": 152.35423278808594,
      "low": 150.95823669433594,
      "close": 151.06777954101562,
      "volume": 1589974.625,
      "amount": 231536176.0
    },
    {
      "timestamp": "2025-09-16T12:15:00",
      "open": 150.82205200195312,
      "high": 151.3371124267578,
      "low": 150.47781372070312,
      "close": 150.91754150390625,
      "volume": 2269845.0,
      "amount": 327814400.0
    },
    {
      "timestamp": "2025-09-16T12:20:00",
      "open": 150.5984344482422,
      "high": 150.8329620361328,
      "low": 149.5970001220703,
      "close": 149.94390869140625,
      "volume": 4067535.25,
      "amount": 603867904.0
    },
    {
      "timestamp": "2025-09-16T12:25:00",
      "open": 149.87783813476562,
      "high": 150.1958465576172,
      "low": 149.4357452392578,
      "close": 149.78567504882812,
      "volume": 1981281.75,
      "amount": 289489248.0
    },
    {
      "timestamp": "2025-09-16T12:30:00",
      "open": 149.67019653320312,
      "high": 149.92994689941406,
      "low": 149.2615203857422,
      "close": 149.5441436767578,
      "volume": 1863168.0,
      "amount": 272064288.0
    },
    {
      "timestamp": "2025-09-16T12:35:00",
      "open": 149.5130157470703,
      "high": 150.00587463378906,
      "low": 149.3271026611328,
      "close": 149.83929443359375,
      "volume": 1922636.0,
      "amount": 279921088.0
    },
    {
      "timestamp": "2025-09-16T12:40:00",
      "open": 149.723876953125,
      "high": 150.06947326660156,
      "low": 149.46014404296875,
      "close": 149.8581085205078,
      "volume": 1906227.0,
      "amount": 277699776.0
    },
    {
      "timestamp": "2025-09-16T12:45:00",
      "open": 149.7428741455078,
      "high": 150.7455291748047,
      "low": 149.2280731201172,
      "close": 149.30101013183594,
      "volume": 2364927.25,
      "amount": 346284032.0
    },
    {
      "timestamp": "2025-09-16T12:50:00",
      "open": 149.22256469726562,
      "high": 149.4327850341797,
      "low": 148.5154571533203,
      "close": 148.76626586914062,
      "volume": 2857713.5,
      "amount": 420666528.0
    },
    {
      "timestamp": "2025-09-16T12:55:00",
      "open": 148.54248046875,
      "high": 148.90687561035156,
      "low": 147.91897583007812,
      "close": 148.28204345703125,
      "volume": 1859257.375,
      "amount": 272938560.0
    },
    {
      "timestamp": "2025-09-16T13:00:00",
      "open": 148.28094482421875,
      "high": 148.65428161621094,
      "low": 147.8790283203125,
      "close": 148.31695556640625,
      "volume": 2432316.5,
      "amount": 353846368.0
    },
    {
      "timestamp": "2025-09-16T13:05:00",
      "open": 148.14698791503906,
      "high": 148.57960510253906,
      "low": 147.95492553710938,
      "close": 148.39974975585938,
      "volume": 1941395.5,
      "amount": 280663264.0
    },
    {
      "timestamp": "2025-09-16T13:10:00",
      "open": 148.3328094482422,
      "high": 148.53260803222656,
      "low": 148.27682495117188,
      "close": 148.40875244140625,
      "volume": 1729035.5,
      "amount": 251724480.0
    },
    {
      "timestamp": "2025-09-16T13:15:00",
      "open": 148.2993621826172,
      "high": 148.4424591064453,
      "low": 148.26177978515625,
      "close": 148.35569763183594,
      "volume": 1675163.0,
      "amount": 243239040.0
    },
    {
      "timestamp": "2025-09-16T13:20:00",
      "open": 148.3603515625,
      "high": 148.9738311767578,
      "low": 148.3056182861328,
      "close": 148.91346740722656,
      "volume": 1511552.0,
      "amount": 220946064.0
    },
    {
      "timestamp": "2025-09-16T13:25:00",
      "open": 148.74359130859375,
      "high": 148.98788452148438,
      "low": 148.46743774414062,
      "close": 148.84075927734375,
      "volume": 1098370.625,
      "amount": 156481088.0
    },
    {
      "timestamp": "2025-09-16T13:30:00",
      "open": 148.79039001464844,
      "high": 149.21798706054688,
      "low": 148.66787719726562,
      "close": 149.11318969726562,
      "volume": 1387306.75,
      "amount": 204252960.0
    },
    {
      "timestamp": "2025-09-16T13:35:00",
      "open": 149.1001434326172,
      "high": 149.4661407470703,
      "low": 148.96588134765625,
      "close": 149.3812255859375,
      "volume": 1079821.5,
      "amount": 155662896.0
    },
    {
      "timestamp": "2025-09-16T13:40:00",
      "open": 149.19406127929688,
      "high": 149.25,
      "low": 148.7891845703125,
      "close": 148.95823669433594,
      "volume": 1236152.625,
      "amount": 183947264.0
    },
    {
      "timestamp": "2025-09-16T13:45:00",
      "open": 149.33554077148438,
      "high": 149.46145629882812,
      "low": 148.012451171875,
      "close": 148.06124877929688,
      "volume": 1299305.125,
      "amount": 189295520.0
    },
    {
      "timestamp": "2025-09-16T13:50:00",
      "open": 148.15452575683594,
      "high": 148.20120239257812,
      "low": 147.74746704101562,
      "close": 147.96556091308594,
      "volume": 1328878.25,
      "amount": 198464448.0
    },
    {
      "timestamp": "2025-09-16T13:55:00",
      "open": 147.89437866210938,
      "high": 148.26698303222656,
      "low": 147.7567138671875,
      "close": 148.11639404296875,
      "volume": 1675294.75,
      "amount": 245024528.0
    },
    {
      "timestamp": "2025-09-16T14:00:00",
      "open": 148.12557983398438,
      "high": 148.428955078125,
      "low": 147.95379638671875,
      "close": 148.32127380371094,
      "volume": 1342230.375,
      "amount": 198105776.0
    },
    {
      "timestamp": "2025-09-16T14:05:00",
      "open": 148.10992431640625,
      "high": 148.2707977294922,
      "low": 147.2999267578125,
      "close": 147.50180053710938,
      "volume": 1519411.625,
      "amount": 226359072.0
    },
    {
      "timestamp": "2025-09-16T14:10:00",
      "open": 147.57601928710938,
      "high": 147.60162353515625,
      "low": 146.87107849121094,
      "close": 147.02342224121094,
      "volume": 1699717.625,
      "amount": 247993248.0
    },
    {
      "timestamp": "2025-09-16T14:15:00",
      "open": 146.9677276611328,
      "high": 147.61773681640625,
      "low": 146.9065704345703,
      "close": 147.5191192626953,
      "volume": 1765090.125,
      "amount": 255947760.0
    },
    {
      "timestamp": "2025-09-16T14:20:00",
      "open": 147.48878479003906,
      "high": 147.70469665527344,
      "low": 147.50955200195312,
      "close": 147.75587463378906,
      "volume": 1506605.0,
      "amount": 214835136.0
    },
    {
      "timestamp": "2025-09-16T14:25:00",
      "open": 147.63763427734375,
      "high": 147.94223022460938,
      "low": 147.38429260253906,
      "close": 147.75503540039062,
      "volume": 1721558.75,
      "amount": 251689840.0
    },
    {
      "timestamp": "2025-09-16T14:30:00",
      "open": 147.79444885253906,
      "high": 147.9344940185547,
      "low": 147.79942321777344,
      "close": 147.8570098876953,
      "volume": 1570923.25,
      "amount": 228976864.0
    },
    {
      "timestamp": "2025-09-16T14:35:00",
      "open": 147.8245391845703,
      "high": 148.09974670410156,
      "low": 147.68995666503906,
      "close": 148.02914428710938,
      "volume": 1359325.875,
      "amount": 200963488.0
    },
    {
      "timestamp": "2025-09-16T14:40:00",
      "open": 148.406982421875,
      "high": 148.89439392089844,
      "low": 147.5498504638672,
      "close": 147.6472930908203,
      "volume": 1442419.5,
      "amount": 205475152.0
    },
    {
      "timestamp": "2025-09-16T14:45:00",
      "open": 147.7317352294922,
      "high": 147.89649963378906,
      "low": 147.53424072265625,
      "close": 147.69873046875,
      "volume": 1774308.0,
      "amount": 259099472.0
    },
    {
      "timestamp": "2025-09-16T14:50:00",
      "open": 147.7996063232422,
      "high": 148.13232421875,
      "low": 147.6748504638672,
      "close": 148.06170654296875,
      "volume": 1381707.0,
      "amount": 205144656.0
    },
    {
      "timestamp": "2025-09-16T14:55:00",
      "open": 147.91505432128906,
      "high": 147.96371459960938,
      "low": 147.40994262695312,
      "close": 147.5823211669922,
      "volume": 2217072.25,
      "amount": 327392192.0
    },
    {
      "timestamp": "2025-09-16T15:00:00",
      "open": 147.49801635742188,
      "high": 147.91860961914062,
      "low": 147.22711181640625,
      "close": 147.60044860839844,
      "volume": 5243887.5,
      "amount": 773169280.0
    },
    {
      "timestamp": "2025-09-16T15:05:00",
      "open": 143.9557647705078,
      "high": 144.27320861816406,
      "low": 139.6492919921875,
      "close": 140.8081512451172,
      "volume": 17053282.0,
      "amount": 2498799104.0
    },
    {
      "timestamp": "2025-09-16T15:10:00",
      "open": 139.81375122070312,
      "high": 141.3671112060547,
      "low": 138.67532348632812,
      "close": 140.30117797851562,
      "volume": 10672066.0,
      "amount": 1517671168.0
    },
    {
      "timestamp": "2025-09-16T15:15:00",
      "open": 139.96678161621094,
      "high": 140.39073181152344,
      "low": 137.89503479003906,
      "close": 138.6493377685547,
      "volume": 8141275.5,
      "amount": 1172781312.0
    },
    {
      "timestamp": "2025-09-16T15:20:00",
      "open": 137.95864868164062,
      "high": 139.64141845703125,
      "low": 137.46060180664062,
      "close": 139.07717895507812,
      "volume": 7248509.0,
      "amount": 1035998080.0
    },
    {
      "timestamp": "2025-09-16T15:25:00",
      "open": 139.684326171875,
      "high": 140.3565216064453,
      "low": 139.13612365722656,
      "close": 139.53656005859375,
      "volume": 4647179.5,
      "amount": 668453184.0
    },
    {
      "timestamp": "2025-09-16T15:30:00",
      "open": 139.6071319580078,
      "high": 139.62525939941406,
      "low": 138.2980194091797,
      "close": 138.36160278320312,
      "volume": 4973026.0,
      "amount": 710507776.0
    },
    {
      "timestamp": "2025-09-16T15:35:00",
      "open": 138.76792907714844,
      "high": 139.9381561279297,
      "low": 138.6023406982422,
      "close": 139.68296813964844,
      "volume": 2869016.0,
      "amount": 409851360.0
    },
    {
      "timestamp": "2025-09-16T15:40:00",
      "open": 139.62002563476562,
      "high": 140.16500854492188,
      "low": 138.90118408203125,
      "close": 139.75144958496094,
      "volume": 3659026.0,
      "amount": 528465632.0
    },
    {
      "timestamp": "2025-09-16T15:45:00",
      "open": 139.97091674804688,
      "high": 140.42958068847656,
      "low": 139.60008239746094,
      "close": 140.0522918701172,
      "volume": 1927634.75,
      "amount": 278014592.0
    },
    {
      "timestamp": "2025-09-16T15:50:00",
      "open": 140.06069946289062,
      "high": 139.9951629638672,
      "low": 139.21998596191406,
      "close": 139.2093505859375,
      "volume": 2722790.25,
      "amount": 395333568.0
    },
    {
      "timestamp": "2025-09-16T15:55:00",
      "open": 139.42604064941406,
      "high": 139.78903198242188,
      "low": 139.18280029296875,
      "close": 139.58692932128906,
      "volume": 1883117.25,
      "amount": 267908272.0
    },
    {
      "timestamp": "2025-09-16T16:00:00",
      "open": 139.70404052734375,
      "high": 140.20913696289062,
      "low": 139.60409545898438,
      "close": 140.06182861328125,
      "volume": 1715654.25,
      "amount": 246989120.0
    },
    {
      "timestamp": "2025-09-16T16:05:00",
      "open": 139.69403076171875,
      "high": 140.2871856689453,
      "low": 139.2871856689453,
      "close": 139.9821319580078,
      "volume": 2869594.0,
      "amount": 415493312.0
    },
    {
      "timestamp": "2025-09-16T16:10:00",
      "open": 139.85324096679688,
      "high": 139.81298828125,
      "low": 139.04063415527344,
      "close": 139.12120056152344,
      "volume": 1833190.75,
      "amount": 262101120.0
    },
    {
      "timestamp": "2025-09-16T16:15:00",
      "open": 139.1430206298828,
      "high": 139.27952575683594,
      "low": 138.67799377441406,
      "close": 138.84765625,
      "volume": 1736460.5,
      "amount": 247990976.0
    },
    {
      "timestamp": "2025-09-16T16:20:00",
      "open": 138.90469360351562,
      "high": 139.58001708984375,
      "low": 138.58570861816406,
      "close": 139.35972595214844,
      "volume": 1623240.375,
      "amount": 225649952.0
    },
    {
      "timestamp": "2025-09-16T16:25:00",
      "open": 139.53565979003906,
      "high": 139.88270568847656,
      "low": 139.3658905029297,
      "close": 139.6968994140625,
      "volume": 1211524.125,
      "amount": 175719968.0
    },
    {
      "timestamp": "2025-09-16T16:30:00",
      "open": 139.6548309326172,
      "high": 139.60194396972656,
      "low": 138.97926330566406,
      "close": 139.04783630371094,
      "volume": 2069046.5,
      "amount": 301959680.0
    },
    {
      "timestamp": "2025-09-16T16:35:00",
      "open": 139.2595977783203,
      "high": 139.53805541992188,
      "low": 138.84776306152344,
      "close": 139.0987091064453,
      "volume": 1387427.875,
      "amount": 204830864.0
    },
    {
      "timestamp": "2025-09-16T16:40:00",
      "open": 139.12686157226562,
      "high": 139.17213439941406,
      "low": 138.66973876953125,
      "close": 138.78753662109375,
      "volume": 1580043.625,
      "amount": 226086352.0
    },
    {
      "timestamp": "2025-09-16T16:45:00",
      "open": 138.49594116210938,
      "high": 139.43017578125,
      "low": 138.26776123046875,
      "close": 139.2468719482422,
      "volume": 2792655.5,
      "amount": 398722432.0
    },
    {
      "timestamp": "2025-09-16T16:50:00",
      "open": 139.31735229492188,
      "high": 139.6492919921875,
      "low": 139.16146850585938,
      "close": 139.4640655517578,
      "volume": 1271455.375,
      "amount": 184202752.0
    },
    {
      "timestamp": "2025-09-16T16:55:00",
      "open": 139.32489013671875,
      "high": 139.3100128173828,
      "low": 138.737060546875,
      "close": 138.8008575439453,
      "volume": 1528489.75,
      "amount": 222084768.0
    },
    {
      "timestamp": "2025-09-16T17:00:00",
      "open": 138.82737731933594,
      "high": 138.93994140625,
      "low": 138.44979858398438,
      "close": 138.61451721191406,
      "volume": 1541448.625,
      "amount": 221940400.0
    },
    {
      "timestamp": "2025-09-16T17:05:00",
      "open": 138.6275177001953,
      "high": 138.76588439941406,
      "low": 138.28688049316406,
      "close": 138.47344970703125,
      "volume": 1524630.5,
      "amount": 219043136.0
    },
    {
      "timestamp": "2025-09-16T17:10:00",
      "open": 138.58786010742188,
      "high": 138.8429412841797,
      "low": 138.387939453125,
      "close": 138.674072265625,
      "volume": 1557901.375,
      "amount": 222350144.0
    },
    {
      "timestamp": "2025-09-16T17:15:00",
      "open": 138.64710998535156,
      "high": 139.17044067382812,
      "low": 138.2987518310547,
      "close": 138.99501037597656,
      "volume": 1456969.125,
      "amount": 203942672.0
    },
    {
      "timestamp": "2025-09-16T17:20:00",
      "open": 138.9881591796875,
      "high": 138.97991943359375,
      "low": 138.42819213867188,
      "close": 138.5181121826172,
      "volume": 1449468.875,
      "amount": 211097472.0
    },
    {
      "timestamp": "2025-09-16T17:25:00",
      "open": 138.58863830566406,
      "high": 138.632080078125,
      "low": 138.3022918701172,
      "close": 138.39393615722656,
      "volume": 1000007.125,
      "amount": 147427216.0
    },
    {
      "timestamp": "2025-09-16T17:30:00",
      "open": 138.5232391357422,
      "high": 138.67686462402344,
      "low": 138.34567260742188,
      "close": 138.56988525390625,
      "volume": 1097915.875,
      "amount": 157950400.0
    },
    {
      "timestamp": "2025-09-16T17:35:00",
      "open": 138.4818115234375,
      "high": 138.55517578125,
      "low": 138.15480041503906,
      "close": 138.31454467773438,
      "volume": 1355695.625,
      "amount": 195476464.0
    },
    {
      "timestamp": "2025-09-16T17:40:00",
      "open": 137.41297912597656,
      "high": 138.4654541015625,
      "low": 136.66448974609375,
      "close": 138.32577514648438,
      "volume": 2864803.0,
      "amount": 409956480.0
    },
    {
      "timestamp": "2025-09-16T17:45:00",
      "open": 137.93515014648438,
      "high": 138.8933563232422,
      "low": 137.6363067626953,
      "close": 138.67030334472656,
      "volume": 2225696.75,
      "amount": 316016704.0
    },
    {
      "timestamp": "2025-09-16T17:50:00",
      "open": 138.77554321289062,
      "high": 138.89266967773438,
      "low": 137.9264373779297,
      "close": 138.20814514160156,
      "volume": 1090409.125,
      "amount": 166928064.0
    },
    {
      "timestamp": "2025-09-16T17:55:00",
      "open": 138.40863037109375,
      "high": 138.5222930908203,
      "low": 138.0286865234375,
      "close": 138.22349548339844,
      "volume": 1966654.25,
      "amount": 285484320.0
    },
    {
      "timestamp": "2025-09-16T18:00:00",
      "open": 138.257568359375,
      "high": 138.5068359375,
      "low": 137.73800659179688,
      "close": 138.13128662109375,
      "volume": 1073488.125,
      "amount": 164179248.0
    },
    {
      "timestamp": "2025-09-16T18:05:00",
      "open": 138.15965270996094,
      "high": 138.22601318359375,
      "low": 137.9429168701172,
      "close": 138.05276489257812,
      "volume": 919212.75,
      "amount": 137054304.0
    },
    {
      "timestamp": "2025-09-16T18:10:00",
      "open": 138.13369750976562,
      "high": 138.7963104248047,
      "low": 137.8847198486328,
      "close": 138.6791229248047,
      "volume": 1279280.0,
      "amount": 181240080.0
    },
    {
      "timestamp": "2025-09-16T18:15:00",
      "open": 138.6365203857422,
      "high": 138.58502197265625,
      "low": 138.19944763183594,
      "close": 138.24530029296875,
      "volume": 903365.5,
      "amount": 136290912.0
    },
    {
      "timestamp": "2025-09-16T18:20:00",
      "open": 138.28814697265625,
      "high": 138.28952026367188,
      "low": 138.0272216796875,
      "close": 138.11936950683594,
      "volume": 860439.875,
      "amount": 129609200.0
    },
    {
      "timestamp": "2025-09-16T18:25:00",
      "open": 138.14263916015625,
      "high": 138.1569061279297,
      "low": 137.92254638671875,
      "close": 138.03628540039062,
      "volume": 827007.25,
      "amount": 124873152.0
    },
    {
      "timestamp": "2025-09-16T18:30:00",
      "open": 138.04200744628906,
      "high": 138.19041442871094,
      "low": 137.80979919433594,
      "close": 138.0192108154297,
      "volume": 1244914.25,
      "amount": 181397120.0
    },
    {
      "timestamp": "2025-09-16T18:35:00",
      "open": 138.00851440429688,
      "high": 137.9921417236328,
      "low": 137.427001953125,
      "close": 137.4619598388672,
      "volume": 1916435.75,
      "amount": 277184256.0
    },
    {
      "timestamp": "2025-09-16T18:40:00",
      "open": 137.5565185546875,
      "high": 137.890869140625,
      "low": 137.4302978515625,
      "close": 137.80885314941406,
      "volume": 1995137.375,
      "amount": 286893056.0
    },
    {
      "timestamp": "2025-09-16T18:45:00",
      "open": 137.793212890625,
      "high": 137.97103881835938,
      "low": 137.56231689453125,
      "close": 137.7889862060547,
      "volume": 1464105.75,
      "amount": 211136576.0
    },
    {
      "timestamp": "2025-09-16T18:50:00",
      "open": 137.78778076171875,
      "high": 137.85398864746094,
      "low": 137.60580444335938,
      "close": 137.72442626953125,
      "volume": 949439.125,
      "amount": 142266080.0
    },
    {
      "timestamp": "2025-09-16T18:55:00",
      "open": 137.73220825195312,
      "high": 137.92141723632812,
      "low": 137.5488739013672,
      "close": 137.77581787109375,
      "volume": 1324441.625,
      "amount": 193480816.0
    },
    {
      "timestamp": "2025-09-16T19:00:00",
      "open": 137.68658447265625,
      "high": 137.72625732421875,
      "low": 137.2838134765625,
      "close": 137.36349487304688,
      "volume": 1416595.25,
      "amount": 207927504.0
    },
    {
      "timestamp": "2025-09-16T19:05:00",
      "open": 137.31878662109375,
      "high": 137.43017578125,
      "low": 137.03347778320312,
      "close": 137.18113708496094,
      "volume": 1433641.75,
      "amount": 209941632.0
    },
    {
      "timestamp": "2025-09-16T19:10:00",
      "open": 137.1394805908203,
      "high": 137.2722930908203,
      "low": 136.8744659423828,
      "close": 137.04537963867188,
      "volume": 1439294.125,
      "amount": 210787104.0
    },
    {
      "timestamp": "2025-09-16T19:15:00",
      "open": 137.08204650878906,
      "high": 137.16990661621094,
      "low": 136.75289916992188,
      "close": 136.86318969726562,
      "volume": 1991196.0,
      "amount": 288188832.0
    },
    {
      "timestamp": "2025-09-16T19:20:00",
      "open": 137.017333984375,
      "high": 137.21449279785156,
      "low": 136.89234924316406,
      "close": 137.13900756835938,
      "volume": 991994.25,
      "amount": 147931728.0
    },
    {
      "timestamp": "2025-09-16T19:25:00",
      "open": 137.0907440185547,
      "high": 137.18031311035156,
      "low": 136.76678466796875,
      "close": 136.9013214111328,
      "volume": 1380261.5,
      "amount": 203965648.0
    },
    {
      "timestamp": "2025-09-16T19:30:00",
      "open": 137.02398681640625,
      "high": 137.1963348388672,
      "low": 136.9091033935547,
      "close": 137.1506805419922,
      "volume": 928517.0,
      "amount": 139663952.0
    },
    {
      "timestamp": "2025-09-16T19:35:00",
      "open": 137.13931274414062,
      "high": 137.16712951660156,
      "low": 136.7557830810547,
      "close": 136.8136444091797,
      "volume": 1893430.375,
      "amount": 274917504.0
    },
    {
      "timestamp": "2025-09-16T19:40:00",
      "open": 136.8153839111328,
      "high": 136.9262237548828,
      "low": 136.33204650878906,
      "close": 136.45726013183594,
      "volume": 2750613.5,
      "amount": 396558944.0
    },
    {
      "timestamp": "2025-09-16T19:45:00",
      "open": 136.67581176757812,
      "high": 137.14300537109375,
      "low": 136.5929412841797,
      "close": 137.08164978027344,
      "volume": 2137499.0,
      "amount": 307210976.0
    },
    {
      "timestamp": "2025-09-16T19:50:00",
      "open": 136.99002075195312,
      "high": 137.06671142578125,
      "low": 136.58287048339844,
      "close": 136.73699951171875,
      "volume": 1581043.5,
      "amount": 232058000.0
    }
  ],
  "actual_data": [
    {
      "timestamp": "2025-09-16T09:55:00",
      "open": 155.2,
      "high": 155.9,
      "low": 155.0,
      "close": 155.9,
      "volume": 2258200.0,
      "amount": 0.0
    },
    {
      "timestamp": "2025-09-16T10:00:00",
      "open": 156.0,
      "high": 156.0,
      "low": 155.1,
      "close": 155.3,
      "volume": 1954300.0,
      "amount": 0.0
    },
    {
      "timestamp": "2025-09-16T10:05:00",
      "open": 155.3,
      "high": 155.3,
      "low": 153.9,
      "close": 154.0,
      "volume": 3423000.0,
      "amount": 0.0
    },
    {
      "timestamp": "2025-09-16T10:10:00",
      "open": 154.0,
      "high": 154.5,
      "low": 154.0,
      "close": 154.2,
      "volume": 2027500.0,
      "amount": 0.0
    },
    {
      "timestamp": "2025-09-16T10:15:00",
      "open": 154.1,
      "high": 154.7,
      "low": 154.1,
      "close": 154.7,
      "volume": 1544400.0,
      "amount": 0.0
    },
    {
      "timestamp": "2025-09-16T10:20:00",
      "open": 154.6,
      "high": 154.9,
      "low": 154.4,
      "close": 154.5,
      "volume": 1516200.0,
      "amount": 0.0
    },
    {
      "timestamp": "2025-09-16T10:25:00",
      "open": 154.5,
      "high": 154.5,
      "low": 153.8,
      "close": 153.8,
      "volume": 2516900.0,
      "amount": 0.0
    },
    {
      "timestamp": "2025-09-16T10:30:00",
      "open": 153.9,
      "high": 154.0,
      "low": 153.4,
      "close": 153.6,
      "volume": 2645900.0,
      "amount": 0.0
    },
    {
      "timestamp": "2025-09-16T10:35:00",
      "open": 153.6,
      "high": 153.9,
      "low": 153.1,
      "close": 153.5,
      "volume": 2048800.0,
      "amount": 0.0
    },
    {
      "timestamp": "2025-09-16T10:40:00",
      "open": 153.4,
      "high": 153.5,
      "low": 152.5,
      "close": 152.6,
      "volume": 2867000.0,
      "amount": 0.0
    },
    {
      "timestamp": "2025-09-16T10:45:00",
      "open": 152.6,
      "high": 153.3,
      "low": 152.5,
      "close": 153.1,
      "volume": 2527200.0,
      "amount": 0.0
    },
    {
      "timestamp": "2025-09-16T10:50:00",
      "open": 153.1,
      "high": 154.4,
      "low": 152.9,
      "close": 154.3,
      "volume": 2615700.0,
      "amount": 0.0
    },
    {
      "timestamp": "2025-09-16T10:55:00",
      "open": 154.3,
      "high": 154.4,
      "low": 153.6,
      "close": 153.7,
      "volume": 1009600.0,
      "amount": 0.0
    },
    {
      "timestamp": "2025-09-16T11:00:00",
      "open": 153.7,
      "high": 153.8,
      "low": 153.4,
      "close": 153.8,
      "volume": 914400.0,
      "amount": 0.0
    },
    {
      "timestamp": "2025-09-16T11:05:00",
      "open": 153.8,
      "high": 153.9,
      "low": 153.5,
      "close": 153.9,
      "volume": 880300.0,
      "amount": 0.0
    },
    {
      "timestamp": "2025-09-16T11:10:00",
      "open": 153.9,
      "high": 154.5,
      "low": 153.8,
      "close": 154.4,
      "volume": 1209900.0,
      "amount": 0.0
    },
    {
      "timestamp": "2025-09-16T11:15:00",
      "open": 154.4,
      "high": 154.5,
      "low": 154.2,
      "close": 154.4,
      "volume": 1055000.0,
      "amount": 0.0
    },
    {
      "timestamp": "2025-09-16T11:20:00",
      "open": 154.3,
      "high": 154.3,
      "low": 153.8,
      "close": 153.9,
      "volume": 900600.0,
      "amount": 0.0
    },
    {
      "timestamp": "2025-09-16T11:25:00",
      "open": 153.9,
      "high": 154.5,
      "low": 153.8,
      "close": 154.5,
      "volume": 771200.0,
      "amount": 0.0
    },
    {
      "timestamp": "2025-09-16T11:30:00",
      "open": 154.4,
      "high": 154.9,
      "low": 154.3,
      "close": 154.9,
      "volume": 768800.0,
      "amount": 0.0
    },
    {
      "timestamp": "2025-09-16T11:35:00",
      "open": 154.8,
      "high": 154.9,
      "low": 154.6,
      "close": 154.8,
      "volume": 829700.0,
      "amount": 0.0
    },
    {
      "timestamp": "2025-09-16T11:40:00",
      "open": 154.7,
      "high": 154.8,
      "low": 154.4,
      "close": 154.5,
      "volume": 496200.0,
      "amount": 0.0
    },
    {
      "timestamp": "2025-09-16T11:45:00",
      "open": 154.4,
      "high": 154.6,
      "low": 154.2,
      "close": 154.3,
      "volume": 554900.0,
      "amount": 0.0
    },
    {
      "timestamp": "2025-09-16T11:50:00",
      "open": 154.3,
      "high": 154.3,
      "low": 154.1,
      "close": 154.1,
      "volume": 361700.0,
      "amount": 0.0
    },
    {
      "timestamp": "2025-09-16T11:55:00",
      "open": 154.1,
      "high": 154.2,
      "low": 153.8,
      "close": 153.9,
      "volume": 718500.0,
      "amount": 0.0
    },
    {
      "timestamp": "2025-09-16T12:00:00",
      "open": 154.0,
      "high": 154.1,
      "low": 153.8,
      "close": 154.1,
      "volume": 633900.0,
      "amount": 0.0
    },
    {
      "timestamp": "2025-09-16T13:05:00",
      "open": 154.1,
      "high": 154.3,
      "low": 153.8,
      "close": 154.0,
      "volume": 1614200.0,
      "amount": 0.0
    },
    {
      "timestamp": "2025-09-16T13:10:00",
      "open": 154.1,
      "high": 154.2,
      "low": 153.9,
      "close": 153.9,
      "volume": 793800.0,
      "amount": 0.0
    },
    {
      "timestamp": "2025-09-16T13:15:00",
      "open": 154.0,
      "high": 154.1,
      "low": 153.8,
      "close": 154.0,
      "volume": 1101200.0,
      "amount": 0.0
    },
    {
      "timestamp": "2025-09-16T13:20:00",
      "open": 153.9,
      "high": 154.0,
      "low": 153.3,
      "close": 153.4,
      "volume": 1421000.0,
      "amount": 0.0
    },
    {
      "timestamp": "2025-09-16T13:25:00",
      "open": 153.4,
      "high": 153.6,
      "low": 153.3,
      "close": 153.5,
      "volume": 775200.0,
      "amount": 0.0
    },
    {
      "timestamp": "2025-09-16T13:30:00",
      "open": 153.5,
      "high": 153.8,
      "low": 153.4,
      "close": 153.6,
      "volume": 722100.0,
      "amount": 0.0
    },
    {
      "timestamp": "2025-09-16T13:35:00",
      "open": 153.7,
      "high": 153.9,
      "low": 153.5,
      "close": 153.7,
      "volume": 741200.0,
      "amount": 0.0
    },
    {
      "timestamp": "2025-09-16T13:40:00",
      "open": 153.7,
      "high": 153.8,
      "low": 153.6,
      "close": 153.8,
      "volume": 592800.0,
      "amount": 0.0
    },
    {
      "timestamp": "2025-09-16T13:45:00",
      "open": 153.8,
      "high": 153.9,
      "low": 153.5,
      "close": 153.7,
      "volume": 997900.0,
      "amount": 0.0
    },
    {
      "timestamp": "2025-09-16T13:50:00",
      "open": 153.8,
      "high": 154.0,
      "low": 153.6,
      "close": 153.8,
      "volume": 1104200.0,
      "amount": 0.0
    },
    {
      "timestamp": "2025-09-16T13:55:00",
      "open": 153.8,
      "high": 154.2,
      "low": 153.6,
      "close": 154.0,
      "volume": 1167100.0,
      "amount": 0.0
    },
    {
      "timestamp": "2025-09-16T14:00:00",
      "open": 154.0,
      "high": 154.7,
      "low": 154.0,
      "close": 154.7,
      "volume": 1116400.0,
      "amount": 0.0
    },
    {
      "timestamp": "2025-09-16T14:05:00",
      "open": 154.7,
      "high": 154.9,
      "low": 154.4,
      "close": 154.8,
      "volume": 1800800.0,
      "amount": 0.0
    },
    {
      "timestamp": "2025-09-16T14:10:00",
      "open": 154.8,
      "high": 154.9,
      "low": 154.2,
      "close": 154.3,
      "volume": 1062500.0,
      "amount": 0.0
    },
    {
      "timestamp": "2025-09-16T14:15:00",
      "open": 154.4,
      "high": 154.4,
      "low": 153.9,
      "close": 154.2,
      "volume": 689000.0,
      "amount": 0.0
    },
    {
      "timestamp": "2025-09-16T14:20:00",
      "open": 154.2,
      "high": 154.3,
      "low": 153.8,
      "close": 153.9,
      "volume": 1053800.0,
      "amount": 0.0
    },
    {
      "timestamp": "2025-09-16T14:25:00",
      "open": 153.9,
      "high": 154.1,
      "low": 153.8,
      "close": 153.8,
      "volume": 1036800.0,
      "amount": 0.0
    },
    {
      "timestamp": "2025-09-16T14:30:00",
      "open": 153.8,
      "high": 154.1,
      "low": 153.8,
      "close": 154.1,
      "volume": 754100.0,
      "amount": 0.0
    },
    {
      "timestamp": "2025-09-16T14:35:00",
      "open": 154.0,
      "high": 154.2,
      "low": 153.9,
      "close": 154.1,
      "volume": 691600.0,
      "amount": 0.0
    },
    {
      "timestamp": "2025-09-16T14:40:00",
      "open": 154.1,
      "high": 154.6,
      "low": 154.0,
      "close": 154.4,
      "volume": 873900.0,
      "amount": 0.0
    },
    {
      "timestamp": "2025-09-16T14:45:00",
      "open": 154.5,
      "high": 154.6,
      "low": 154.3,
      "close": 154.5,
      "volume": 702100.0,
      "amount": 0.0
    },
    {
      "timestamp": "2025-09-16T14:50:00",
      "open": 154.4,
      "high": 154.5,
      "low": 154.3,
      "close": 154.4,
      "volume": 444500.0,
      "amount": 0.0
    },
    {
      "timestamp": "2025-09-16T14:55:00",
      "open": 154.4,
      "high": 154.6,
      "low": 154.3,
      "close": 154.3,
      "volume": 803400.0,
      "amount": 0.0
    },
    {
      "timestamp": "2025-09-16T15:00:00",
      "open": 154.3,
      "high": 154.5,
      "low": 154.3,
      "close": 154.4,
      "volume": 619100.0,
      "amount": 0.0
    },
    {
      "timestamp": "2025-09-16T15:05:00",
      "open": 154.5,
      "high": 154.5,
      "low": 154.0,
      "close": 154.3,
      "volume": 870700.0,
      "amount": 0.0
    },
    {
      "timestamp": "2025-09-16T15:10:00",
      "open": 154.3,
      "high": 154.5,
      "low": 154.2,
      "close": 154.4,
      "volume": 738300.0,
      "amount": 0.0
    },
    {
      "timestamp": "2025-09-16T15:15:00",
      "open": 154.4,
      "high": 154.4,
      "low": 154.0,
      "close": 154.2,
      "volume": 656900.0,
      "amount": 0.0
    },
    {
      "timestamp": "2025-09-16T15:20:00",
      "open": 154.2,
      "high": 154.3,
      "low": 154.1,
      "close": 154.3,
      "volume": 590100.0,
      "amount": 0.0
    },
    {
      "timestamp": "2025-09-16T15:25:00",
      "open": 154.3,
      "high": 154.3,
      "low": 154.1,
      "close": 154.1,
      "volume": 842600.0,
      "amount": 0.0
    },
    {
      "timestamp": "2025-09-16T15:30:00",
      "open": 154.2,
      "high": 154.3,
      "low": 154.1,
      "close": 154.1,
      "volume": 793000.0,
      "amount": 0.0
    },
    {
      "timestamp": "2025-09-16T15:35:00",
      "open": 154.2,
      "high": 154.4,
      "low": 154.0,
      "close": 154.2,
      "volume": 1565300.0,
      "amount": 0.0
    },
    {
      "timestamp": "2025-09-16T15:40:00",
      "open": 154.2,
      "high": 154.3,
      "low": 154.0,
      "close": 154.0,
      "volume": 789000.0,
      "amount": 0.0
    },
    {
      "timestamp": "2025-09-16T15:45:00",
      "open": 154.0,
      "high": 154.1,
      "low": 153.7,
      "close": 153.8,
      "volume": 1229000.0,
      "amount": 0.0
    },
    {
      "timestamp": "2025-09-16T15:50:00",
      "open": 153.8,
      "high": 154.0,
      "low": 153.6,
      "close": 153.7,
      "volume": 1132600.0,
      "amount": 0.0
    },
    {
      "timestamp": "2025-09-16T15:55:00",
      "open": 153.7,
      "high": 153.7,
      "low": 153.3,
      "close": 153.6,
      "volume": 2069200.0,
      "amount": 0.0
    },
    {
      "timestamp": "2025-09-16T16:00:00",
      "open": 153.6,
      "high": 153.7,
      "low": 153.2,
      "close": 153.5,
      "volume": 7221000.0,
      "amount": 0.0
    },
    {
      "timestamp": "2025-09-17T09:35:00",
      "open": 157.7,
      "high": 158.4,
      "low": 156.7,
      "close": 157.6,
      "volume": 14167900.0,
      "amount": 0.0
    },
    {
      "timestamp": "2025-09-17T09:40:00",
      "open": 157.6,
      "high": 158.4,
      "low": 157.6,
      "close": 157.8,
      "volume": 5663800.0,
      "amount": 0.0
    },
    {
      "timestamp": "2025-09-17T09:45:00",
      "open": 157.7,
      "high": 158.0,
      "low": 157.7,
      "close": 157.9,
      "volume": 2393800.0,
      "amount": 0.0
    },
    {
      "timestamp": "2025-09-17T09:50:00",
      "open": 158.0,
      "high": 158.8,
      "low": 157.9,
      "close": 158.7,
      "volume": 6081800.0,
      "amount": 0.0
    },
    {
      "timestamp": "2025-09-17T09:55:00",
      "open": 158.8,
      "high": 159.0,
      "low": 158.3,
      "close": 158.4,
      "volume": 3973400.0,
      "amount": 0.0
    },
    {
      "timestamp": "2025-09-17T10:00:00",
      "open": 158.5,
      "high": 158.5,
      "low": 157.8,
      "close": 158.0,
      "volume": 2734700.0,
      "amount": 0.0
    },
    {
      "timestamp": "2025-09-17T10:05:00",
      "open": 157.9,
      "high": 158.8,
      "low": 157.8,
      "close": 158.7,
      "volume": 2040900.0,
      "amount": 0.0
    },
    {
      "timestamp": "2025-09-17T10:10:00",
      "open": 158.7,
      "high": 159.1,
      "low": 158.4,
      "close": 158.5,
      "volume": 3620600.0,
      "amount": 0.0
    },
    {
      "timestamp": "2025-09-17T10:15:00",
      "open": 158.5,
      "high": 158.8,
      "low": 158.1,
      "close": 158.6,
      "volume": 1254700.0,
      "amount": 0.0
    },
    {
      "timestamp": "2025-09-17T10:20:00",
      "open": 158.6,
      "high": 159.5,
      "low": 158.6,
      "close": 159.5,
      "volume": 2495700.0,
      "amount": 0.0
    },
    {
      "timestamp": "2025-09-17T10:25:00",
      "open": 159.5,
      "high": 159.5,
      "low": 159.0,
      "close": 159.4,
      "volume": 1954400.0,
      "amount": 0.0
    },
    {
      "timestamp": "2025-09-17T10:30:00",
      "open": 159.4,
      "high": 159.6,
      "low": 158.5,
      "close": 158.5,
      "volume": 2227500.0,
      "amount": 0.0
    },
    {
      "timestamp": "2025-09-17T10:35:00",
      "open": 158.5,
      "high": 159.2,
      "low": 158.3,
      "close": 159.1,
      "volume": 1409000.0,
      "amount": 0.0
    },
    {
      "timestamp": "2025-09-17T10:40:00",
      "open": 159.2,
      "high": 159.5,
      "low": 159.1,
      "close": 159.5,
      "volume": 1509800.0,
      "amount": 0.0
    },
    {
      "timestamp": "2025-09-17T10:45:00",
      "open": 159.6,
      "high": 159.7,
      "low": 159.3,
      "close": 159.5,
      "volume": 1807500.0,
      "amount": 0.0
    },
    {
      "timestamp": "2025-09-17T10:50:00",
      "open": 159.5,
      "high": 159.9,
      "low": 159.4,
      "close": 159.7,
      "volume": 4218900.0,
      "amount": 0.0
    },
    {
      "timestamp": "2025-09-17T10:55:00",
      "open": 159.7,
      "high": 161.0,
      "low": 159.7,
      "close": 160.9,
      "volume": 8841700.0,
      "amount": 0.0
    },
    {
      "timestamp": "2025-09-17T11:00:00",
      "open": 160.9,
      "high": 160.9,
      "low": 160.1,
      "close": 160.2,
      "volume": 2171300.0,
      "amount": 0.0
    },
    {
      "timestamp": "2025-09-17T11:05:00",
      "open": 160.2,
      "high": 161.3,
      "low": 160.2,
      "close": 161.2,
      "volume": 3198700.0,
      "amount": 0.0
    },
    {
      "timestamp": "2025-09-17T11:10:00",
      "open": 161.3,
      "high": 161.5,
      "low": 160.6,
      "close": 161.1,
      "volume": 2976700.0,
      "amount": 0.0
    },
    {
      "timestamp": "2025-09-17T11:15:00",
      "open": 161.1,
      "high": 161.5,
      "low": 160.8,
      "close": 161.5,
      "volume": 3446300.0,
      "amount": 0.0
    },
    {
      "timestamp": "2025-09-17T11:20:00",
      "open": 161.4,
      "high": 161.9,
      "low": 161.3,
      "close": 161.9,
      "volume": 2696400.0,
      "amount": 0.0
    },
    {
      "timestamp": "2025-09-17T11:25:00",
      "open": 161.8,
      "high": 162.3,
      "low": 161.1,
      "close": 161.2,
      "volume": 5253600.0,
      "amount": 0.0
    },
    {
      "timestamp": "2025-09-17T11:30:00",
      "open": 161.2,
      "high": 161.5,
      "low": 160.6,
      "close": 161.4,
      "volume": 2374200.0,
      "amount": 0.0
    },
    {
      "timestamp": "2025-09-17T11:35:00",
      "open": 161.4,
      "high": 161.7,
      "low": 161.0,
      "close": 161.7,
      "volume": 1423200.0,
      "amount": 0.0
    },
    {
      "timestamp": "2025-09-17T11:40:00",
      "open": 161.7,
      "high": 161.8,
      "low": 160.5,
      "close": 160.6,
      "volume": 1712500.0,
      "amount": 0.0
    },
    {
      "timestamp": "2025-09-17T11:45:00",
      "open": 160.6,
      "high": 160.9,
      "low": 160.5,
      "close": 160.8,
      "volume": 884100.0,
      "amount": 0.0
    },
    {
      "timestamp": "2025-09-17T11:50:00",
      "open": 160.8,
      "high": 161.0,
      "low": 160.7,
      "close": 161.0,
      "volume": 828700.0,
      "amount": 0.0
    },
    {
      "timestamp": "2025-09-17T11:55:00",
      "open": 161.0,
      "high": 161.4,
      "low": 160.9,
      "close": 161.2,
      "volume": 997800.0,
      "amount": 0.0
    },
    {
      "timestamp": "2025-09-17T12:00:00",
      "open": 161.2,
      "high": 161.4,
      "low": 161.0,
      "close": 161.2,
      "volume": 724400.0,
      "amount": 0.0
    },
    {
      "timestamp": "2025-09-17T13:05:00",
      "open": 161.2,
      "high": 161.5,
      "low": 160.5,
      "close": 161.3,
      "volume": 2404000.0,
      "amount": 0.0
    },
    {
      "timestamp": "2025-09-17T13:10:00",
      "open": 161.4,
      "high": 161.4,
      "low": 160.7,
      "close": 160.7,
      "volume": 1446200.0,
      "amount": 0.0
    },
    {
      "timestamp": "2025-09-17T13:15:00",
      "open": 160.8,
      "high": 161.4,
      "low": 160.7,
      "close": 161.3,
      "volume": 936500.0,
      "amount": 0.0
    },
    {
      "timestamp": "2025-09-17T13:20:00",
      "open": 161.3,
      "high": 161.4,
      "low": 160.8,
      "close": 161.1,
      "volume": 1276100.0,
      "amount": 0.0
    },
    {
      "timestamp": "2025-09-17T13:25:00",
      "open": 161.2,
      "high": 161.5,
      "low": 161.1,
      "close": 161.4,
      "volume": 1270900.0,
      "amount": 0.0
    },
    {
      "timestamp": "2025-09-17T13:30:00",
      "open": 161.3,
      "high": 161.6,
      "low": 161.3,
      "close": 161.4,
      "volume": 1304000.0,
      "amount": 0.0
    },
    {
      "timestamp": "2025-09-17T13:35:00",
      "open": 161.5,
      "high": 161.9,
      "low": 161.5,
      "close": 161.9,
      "volume": 1817800.0,
      "amount": 0.0
    },
    {
      "timestamp": "2025-09-17T13:40:00",
      "open": 161.9,
      "high": 162.0,
      "low": 160.7,
      "close": 160.9,
      "volume": 2330800.0,
      "amount": 0.0
    },
    {
      "timestamp": "2025-09-17T13:45:00",
      "open": 161.0,
      "high": 161.7,
      "low": 160.8,
      "close": 161.7,
      "volume": 1791800.0,
      "amount": 0.0
    },
    {
      "timestamp": "2025-09-17T13:50:00",
      "open": 161.7,
      "high": 161.9,
      "low": 161.4,
      "close": 161.4,
      "volume": 2423700.0,
      "amount": 0.0
    },
    {
      "timestamp": "2025-09-17T13:55:00",
      "open": 161.5,
      "high": 161.5,
      "low": 161.1,
      "close": 161.2,
      "volume": 1071200.0,
      "amount": 0.0
    },
    {
      "timestamp": "2025-09-17T14:00:00",
      "open": 161.2,
      "high": 161.4,
      "low": 161.0,
      "close": 161.4,
      "volume": 877900.0,
      "amount": 0.0
    },
    {
      "timestamp": "2025-09-17T14:05:00",
      "open": 161.4,
      "high": 161.9,
      "low": 161.3,
      "close": 161.6,
      "volume": 1546300.0,
      "amount": 0.0
    },
    {
      "timestamp": "2025-09-17T14:10:00",
      "open": 161.7,
      "high": 161.7,
      "low": 161.1,
      "close": 161.4,
      "volume": 1482300.0,
      "amount": 0.0
    },
    {
      "timestamp": "2025-09-17T14:15:00",
      "open": 161.4,
      "high": 161.5,
      "low": 161.2,
      "close": 161.3,
      "volume": 971800.0,
      "amount": 0.0
    },
    {
      "timestamp": "2025-09-17T14:20:00",
      "open": 161.2,
      "high": 161.6,
      "low": 161.2,
      "close": 161.6,
      "volume": 1009900.0,
      "amount": 0.0
    },
    {
      "timestamp": "2025-09-17T14:25:00",
      "open": 161.6,
      "high": 162.0,
      "low": 161.5,
      "close": 161.9,
      "volume": 1056800.0,
      "amount": 0.0
    },
    {
      "timestamp": "2025-09-17T14:30:00",
      "open": 162.0,
      "high": 162.0,
      "low": 161.8,
      "close": 161.9,
      "volume": 1110900.0,
      "amount": 0.0
    },
    {
      "timestamp": "2025-09-17T14:35:00",
      "open": 161.9,
      "high": 162.2,
      "low": 161.8,
      "close": 162.1,
      "volume": 2501200.0,
      "amount": 0.0
    },
    {
      "timestamp": "2025-09-17T14:40:00",
      "open": 162.1,
      "high": 162.2,
      "low": 161.4,
      "close": 162.0,
      "volume": 1519000.0,
      "amount": 0.0
    },
    {
      "timestamp": "2025-09-17T14:45:00",
      "open": 162.0,
      "high": 162.2,
      "low": 161.8,
      "close": 161.9,
      "volume": 1378400.0,
      "amount": 0.0
    },
    {
      "timestamp": "2025-09-17T14:50:00",
      "open": 161.8,
      "high": 162.2,
      "low": 161.8,
      "close": 162.0,
      "volume": 1489700.0,
      "amount": 0.0
    },
    {
      "timestamp": "2025-09-17T14:55:00",
      "open": 162.1,
      "high": 162.2,
      "low": 161.9,
      "close": 162.1,
      "volume": 1496900.0,
      "amount": 0.0
    },
    {
      "timestamp": "2025-09-17T15:00:00",
      "open": 162.1,
      "high": 162.2,
      "low": 161.6,
      "close": 161.7,
      "volume": 1743400.0,
      "amount": 0.0
    },
    {
      "timestamp": "2025-09-17T15:05:00",
      "open": 161.7,
      "high": 161.7,
      "low": 161.0,
      "close": 161.2,
      "volume": 2573000.0,
      "amount": 0.0
    },
    {
      "timestamp": "2025-09-17T15:10:00",
      "open": 161.2,
      "high": 161.7,
      "low": 161.2,
      "close": 161.6,
      "volume": 1341900.0,
      "amount": 0.0
    },
    {
      "timestamp": "2025-09-17T15:15:00",
      "open": 161.6,
      "high": 161.9,
      "low": 161.5,
      "close": 161.8,
      "volume": 795700.0,
      "amount": 0.0
    },
    {
      "timestamp": "2025-09-17T15:20:00",
      "open": 161.8,
      "high": 161.9,
      "low": 161.4,
      "close": 161.5,
      "volume": 1144200.0,
      "amount": 0.0
    }
  ],
  "analysis": {
    "continuity": {
      "last_prediction": {
        "open": 155.5508575439453,
        "high": 156.3904266357422,
        "low": 155.45201110839844,
        "close": 156.0921173095703
      },
      "first_actual": {
        "open": 155.2,
        "high": 155.9,
        "low": 155.0,
        "close": 155.9
      },
      "gaps": {
        "open_gap": 0.35085754394532387,
        "high_gap": 0.4904266357421818,
        "low_gap": 0.4520111083984375,
        "close_gap": 0.19211730957030682
      },
      "gap_percentages": {
        "open_gap_pct": 0.22606800511940972,
        "high_gap_pct": 0.3145777009250685,
        "low_gap_pct": 0.2916200699344758,
        "close_gap_pct": 0.1232311158244431
      }
    }
  }
}